docx_comments_to_text/__init__.py
docx_comments_to_text/cli.py
docx_comments_to_text/docx_parser.py
docx_comments_to_text/docx_processor.py
docx_comments_to_text/text_formatter.py
docx_comments_to_text-0.2.2.dist-info/METADATA
docx_comments_to_text-0.2.2.dist-info/WHEEL
docx_comments_to_text-0.2.2.dist-info/entry_points.txt
docx_comments_to_text-0.2.2.dist-info/top_level.txt
docx_comments_to_text-0.2.2.dist-info/RECORD
