Metadata-Version: 2.4
Name: docx-comments-to-text
Version: 0.2.2
Summary: Extract reviewer comments from .docx files and insert them inline with the text
Author-email: Giorgio Momigliano <gmomigliano@protonmail.com>
License-Expression: MIT
Project-URL: Homepage, https://github.com/platelminto/docx-comments-to-text
Project-URL: Repository, https://github.com/platelminto/docx-comments-to-text
Project-URL: Issues, https://github.com/platelminto/docx-comments-to-text/issues
Keywords: docx,comments,document,text,review
Classifier: Development Status :: 4 - Beta
Classifier: Intended Audience :: End Users/Desktop
Classifier: Programming Language :: Python :: 3
Classifier: Programming Language :: Python :: 3.13
Classifier: Topic :: Office/Business
Classifier: Topic :: Text Processing
Requires-Python: >=3.13
Requires-Dist: python-docx
Requires-Dist: lxml
Requires-Dist: click
Provides-Extra: dev
Requires-Dist: pytest>=8.4.1; extra == "dev"
